odoo/addons/account_invoice_restrict_linked_so/README.rst
odoo/addons/account_invoice_restrict_linked_so/__init__.py
odoo/addons/account_invoice_restrict_linked_so/__manifest__.py
odoo/addons/account_invoice_restrict_linked_so/i18n/account_invoice_restrict_linked_so.pot
odoo/addons/account_invoice_restrict_linked_so/i18n/it.po
odoo/addons/account_invoice_restrict_linked_so/i18n/sl.po
odoo/addons/account_invoice_restrict_linked_so/readme/CONTRIBUTORS.rst
odoo/addons/account_invoice_restrict_linked_so/readme/DESCRIPTION.rst
odoo/addons/account_invoice_restrict_linked_so/readme/USAGE.rst
odoo/addons/account_invoice_restrict_linked_so/static/description/icon.png
odoo/addons/account_invoice_restrict_linked_so/static/description/index.html
odoo/addons/account_invoice_restrict_linked_so/views/account_move.xml
odoo14_addon_account_invoice_restrict_linked_so-14.0.1.0.2.dev10.dist-info/METADATA
odoo14_addon_account_invoice_restrict_linked_so-14.0.1.0.2.dev10.dist-info/WHEEL
odoo14_addon_account_invoice_restrict_linked_so-14.0.1.0.2.dev10.dist-info/top_level.txt
odoo14_addon_account_invoice_restrict_linked_so-14.0.1.0.2.dev10.dist-info/RECORD
