Metadata-Version: 2.1
Name: odoo14-addon-account_invoice_restrict_linked_so
Version: 14.0.1.0.2.dev10
Summary: Restricts editing the Product, Quantity and Unit Price columns for invoice lines that originated in Sales Orders.
Home-page: https://github.com/OCA/account-invoicing
Author: Open Source Integrators, Odoo Community Association (OCA)
Author-email: support@odoo-community.org
License: AGPL-3
Classifier: Programming Language :: Python
Classifier: Framework :: Odoo
Classifier: Framework :: Odoo :: 14.0
Classifier: License :: OSI Approved :: GNU Affero General Public License v3
Requires-Python: >=3.6
Requires-Dist: odoo<14.1dev,>=14.0a
